data_replication/__init__.py
data_replication/admin.py
data_replication/apps.py
data_replication/forms.py
data_replication/models.py
data_replication/tasks.py
data_replication/urls.py
data_replication/views.py
data_replication/backends/__init__.py
data_replication/backends/base.py
data_replication/backends/mongo.py
data_replication/backends/splunk.py
data_replication/fixtures/data_replication/initial_data.json
data_replication/management/__init__.py
data_replication/management/commands/__init__.py
data_replication/management/commands/replicate.py
data_replication/migrations/0001_initial.py
data_replication/migrations/0002_auto_20210722_2316.py
data_replication/migrations/__init__.py
django_data_replication-1.1.5.dist-info/LICENSE.txt
django_data_replication-1.1.5.dist-info/METADATA
django_data_replication-1.1.5.dist-info/WHEEL
django_data_replication-1.1.5.dist-info/top_level.txt
django_data_replication-1.1.5.dist-info/RECORD
