Metadata-Version: 2.1
Name: django-data-replication
Version: 1.1.5
Summary: Django Data Replication for Splunk and/or Mongo
Home-page: https://github.com/icmanage/django-data-replication
Author: Steven Klass
Author-email: sklass@icmanage.com
License: UNKNOWN
Download-URL: https://github.com/icmanage/django-data-replication/archive/1.1.5.tar.gz
Project-URL: Bug Reports, https://github.com/icmanage/django-data-replication/issues
Project-URL: Say Thanks!, http://saythanks.io/to/rh0dium
Project-URL: Source, https://github.com/icmanage/django-data-replication
Keywords: django mongo splunk replication
Platform: UNKNOWN
Classifier: Development Status :: 4 - Beta
Classifier: Environment :: Web Environment
Classifier: Framework :: Django
Classifier: License :: OSI Approved :: MIT License
Classifier: Programming Language :: Python :: 3
Classifier: Programming Language :: Python :: 3.7
Classifier: Programming Language :: Python :: 3.8
Classifier: Programming Language :: Python :: 3.9
License-File: LICENSE.txt
Requires-Dist: django (<4,>=3)
Requires-Dist: celery
Requires-Dist: pymongo
Requires-Dist: requests
